BCFOX/__init__.py
BCFOX/find_elements.py
BCFOX/get_driver.py
BCFOX/invoke_api.py
BCFOX-0.1.5.dist-info/METADATA
BCFOX-0.1.5.dist-info/WHEEL
BCFOX-0.1.5.dist-info/top_level.txt
BCFOX-0.1.5.dist-info/RECORD
