Metadata-Version: 2.1
Name: BCFOX
Version: 0.1.5
Summary: Biblioteca BCFOX
Home-page: https://github.com/GuilhermNeri/BCFOX
Author: Guilherme Neri
Author-email: guilherme.neri@bcfox.com.br
Classifier: Programming Language :: Python :: 3
Classifier: License :: OSI Approved :: MIT License
Classifier: Operating System :: OS Independent
Requires-Python: >=3.6
Requires-Dist: selenium
Requires-Dist: selenium-stealth
Requires-Dist: undetected-chromedriver
Requires-Dist: requests
